youdao_translator.py
youdao_translator-1.0.1.dist-info/LICENSE
youdao_translator-1.0.1.dist-info/METADATA
youdao_translator-1.0.1.dist-info/WHEEL
youdao_translator-1.0.1.dist-info/entry_points.txt
youdao_translator-1.0.1.dist-info/top_level.txt
youdao_translator-1.0.1.dist-info/RECORD
