Metadata-Version: 2.1
Name: youdao-translator
Version: 1.0.1
Summary: simple approach to translate English to Chinese by youdao-translator-cli
Home-page: https://github.com/faris-shi/youdao_translator
Author: Faris Shi
Author-email: faris.shi84@gmail.com
License: MIT
Keywords: youdao translator english cli command
Platform: UNKNOWN
Classifier: Development Status :: 4 - Beta
Classifier: Environment :: Console
Classifier: License :: OSI Approved :: MIT License
Classifier: Intended Audience :: Developers
Classifier: Natural Language :: English
Classifier: Topic :: Utilities
Classifier: Operating System :: OS Independent
Classifier: Programming Language :: Python :: 3
Classifier: Programming Language :: Python :: 3.3
Classifier: Programming Language :: Python :: 3.4
Classifier: Programming Language :: Python :: 3.5
Classifier: Programming Language :: Python :: 3.6
Classifier: Programming Language :: Python :: 3.7
Classifier: Programming Language :: Python :: 3.8
Requires-Dist: pyquery
Requires-Dist: click
Requires-Dist: rich
Requires-Dist: requests
Requires-Dist: playsound
